Metadata-Version: 1.1
Name: appconf
Version: 0.1.11
Summary: library
Home-page: https://github.com/novopl/appconf
Author: Mateusz Klos
Author-email: novopl@gmail.com
License: Apache 2.0
Keywords: library
Platform: UNKNOWN
Classifier: Development Status :: 2 - Pre-Alpha
Classifier: Topic :: Utilities
Classifier: Intended Audience :: Developers
Classifier: Programming Language :: Python
Classifier: Programming Language :: Python :: 3
Classifier: License :: OSI Approved :: Apache Software License
